{
  "parent": "minecraft:recipes/root",
  "criteria": {
    "has_smithing_trim_template": {
      "conditions": {
        "items": [
          {
            "items": "gemcraft:archaic_armor_trim_smithing_template"
          }
        ]
      },
      "trigger": "minecraft:inventory_changed"
    },
    "has_the_recipe": {
      "conditions": {
        "recipe": "gemcraft:archaic"
      },
      "trigger": "minecraft:recipe_unlocked"
    }
  },
  "requirements": [
    [
      "has_the_recipe",
      "has_smithing_trim_template"
    ]
  ],
  "rewards": {
    "recipes": [
      "gemcraft:archaic"
    ]
  }
}